[
    {
        "img": "https://images-na.ssl-images-amazon.com/images/I/51poKKV63GL.jpg",
        "name": "Star Wars VIII : The Last Jedi"
    },
    {
        "img": "http://imgc.allpostersimages.com/img/posters/captain-marvel_u-L-Q1FXWZV0.jpg",
        "name": "Captain Marvel"
    },
    {
        "img": "https://www.reeldeals.com/Images/HomeImages/26296.jpg",
        "name": "Titanic"
    },
    {
        "img": "https://static01.nyt.com/images/2017/09/15/arts/24movie-posters8/24movie-posters8-articleLarge.jpg?quality=75&auto=webp&disable=upscale",
        "name": "The Shining"
    },
    {
        "img": "https://images-na.ssl-images-amazon.com/images/I/71kod5t-q9L._SY679_.jpg",
        "name": "The Incredibles"
    },
    {
        "img": "http://www.blackpearlminute.com/wp-content/uploads/2016/12/Pirates_of_the_Caribbean_movie-299x445.jpg",
        "name": "Pirates of the Caribbean : Curse of the Black Pearl"
    },
    {
        "img": "https://hips.hearstapps.com/hmg-prod.s3.amazonaws.com/images/dkbjs2ouqaazkje-1506021465.jpg?crop=1xw:1xh;center,top&resize=480:*",
        "name": "Tomb Raider"
    },
    {
        "img": "https://images-na.ssl-images-amazon.com/images/I/7151Qmxd3pL._SY679_.jpg",
        "name": "The Mummy"
    }
]
